README
setup.py
OpenSCAD_Minimizer.egg-info/PKG-INFO
OpenSCAD_Minimizer.egg-info/SOURCES.txt
OpenSCAD_Minimizer.egg-info/dependency_links.txt
OpenSCAD_Minimizer.egg-info/entry_points.txt
OpenSCAD_Minimizer.egg-info/top_level.txt
osm/__init__.py
osm/osm.py